radicale_kalabash_token_auth/__init__.py
radicale_kalabash_token_auth-0.1.0.dist-info/METADATA
radicale_kalabash_token_auth-0.1.0.dist-info/WHEEL
radicale_kalabash_token_auth-0.1.0.dist-info/top_level.txt
radicale_kalabash_token_auth-0.1.0.dist-info/RECORD
